Number_generator-1.1.dist-info/METADATA
Number_generator-1.1.dist-info/RECORD
Number_generator-1.1.dist-info/WHEEL
Number_generator-1.1.dist-info/top_level.txt
numbergenerator/__init__.py
numbergenerator/number_generator.py
test/__init__.py
test/test_number_generator.py
