Metadata-Version: 2.1
Name: Number-generator
Version: 1.1
Summary: Random number generation tool
Home-page: https://github.com/iurdaniz7/Number-generator
Author: Ion Urdaniz
Author-email: i.urdaniz7@gmail.com
License: MIT
Platform: UNKNOWN
Classifier: Programming Language :: Python :: 3
Classifier: License :: OSI Approved :: MIT License
Classifier: Operating System :: OS Independent
Requires-Dist: certifi (==2018.4.16)
Requires-Dist: mkl-random (==1.0.1)
Requires-Dist: numpy (==1.14.5)
Requires-Dist: wincertstore (==0.2)
